Metadata-Version: 1.0
Name: soothsayer_utils
Version: 2022.1.19
Summary: Utility functions for Soothsayer
Home-page: https://github.com/jolespin/soothsayer_utils
Author: Josh L. Espinoza
Author-email: jespinoz@jcvi.org
License: BSD-3
Platform: UNKNOWN
